Workbook

Sheet Registro real
A1: PLAN DE INVERSION EN OPCIONES · Registro diario
A2: Objetivo: crecer 10% cada dia de operacion (lun-vie). El BALANCE es la fuente de verdad; el resto se calcula solo.
A4: Capital inicial | B4: 100 | D4: Rendimiento total | E4: =B6/B4 | L4: Calculadora de %
A5: Balance actual | B5: =B4+SUM(F9:F58) | D5: Dias operados | E5: =IFERROR(MAX(C9:C58),0) | L5: Precio compra | M5: 87
A6: Ganancia total | B6: =SUM(F9:F58) | D6: Operaciones | E6: =COUNTA(D9:D58) | L6: Precio venta | M6: 90
L7: Rend. % | M7: =IF(M5=0,"",(M6-M5)/M5)
A8: Fecha | B8: Op # | C8: Dia op. | D8: Activo | E8: Rend. trade % | F8: Ganancia ($) | G8: Balance | H8: % s/ capital | I8: Balance objetivo | J8: Dif. vs plan | L8: Escribe compra y venta; copia el % a la tabla.
A9: 46218 | B9: 1 | C9: 1 | D9: IWM | E9: 0.034482759 | F9: 3 | G9: =IF(F9="","",$B$4+SUM($F$9:F9)) | H9: =IF(F9="","",F9/(G9-F9)) | I9: =IF(C9="","",IFERROR(VLOOKUP(C9,'Plan objetivo 10%'!$A:$C,3,FALSE),"")) | J9: =IF(OR(G9="",I9=""),"",G9-I9)
A10: 46219 | B10: 2 | C10: 2 | D10: IWM | E10: 0.13333333 | F10: 10 | G10: =IF(F10="","",$B$4+SUM($F$9:F10)) | H10: =IF(F10="","",F10/(G10-F10)) | I10: =IF(C10="","",IFERROR(VLOOKUP(C10,'Plan objetivo 10%'!$A:$C,3,FALSE),"")) | J10: =IF(OR(G10="",I10=""),"",G10-I10)
A11: 46220 | B11: 3 | C11: 3 | D11: NVDA | E11: 0.044444444 | F11: 4 | G11: =IF(F11="","",$B$4+SUM($F$9:F11)) | H11: =IF(F11="","",F11/(G11-F11)) | I11: =IF(C11="","",IFERROR(VLOOKUP(C11,'Plan objetivo 10%'!$A:$C,3,FALSE),"")) | J11: =IF(OR(G11="",I11=""),"",G11-I11)
A12: 46220 | B12: 4 | C12: 3 | D12: NFLX | E12: 0.25 | F12: 14 | G12: =IF(F12="","",$B$4+SUM($F$9:F12)) | H12: =IF(F12="","",F12/(G12-F12)) | I12: =IF(C12="","",IFERROR(VLOOKUP(C12,'Plan objetivo 10%'!$A:$C,3,FALSE),"")) | J12: =IF(OR(G12="",I12=""),"",G12-I12)
G13: =IF(F13="","",$B$4+SUM($F$9:F13)) | H13: =IF(F13="","",F13/(G13-F13)) | I13: =IF(C13="","",IFERROR(VLOOKUP(C13,'Plan objetivo 10%'!$A:$C,3,FALSE),"")) | J13: =IF(OR(G13="",I13=""),"",G13-I13)
G14: =IF(F14="","",$B$4+SUM($F$9:F14)) | H14: =IF(F14="","",F14/(G14-F14)) | I14: =IF(C14="","",IFERROR(VLOOKUP(C14,'Plan objetivo 10%'!$A:$C,3,FALSE),"")) | J14: =IF(OR(G14="",I14=""),"",G14-I14)
G15: =IF(F15="","",$B$4+SUM($F$9:F15)) | H15: =IF(F15="","",F15/(G15-F15)) | I15: =IF(C15="","",IFERROR(VLOOKUP(C15,'Plan objetivo 10%'!$A:$C,3,FALSE),"")) | J15: =IF(OR(G15="",I15=""),"",G15-I15)
G16: =IF(F16="","",$B$4+SUM($F$9:F16)) | H16: =IF(F16="","",F16/(G16-F16)) | I16: =IF(C16="","",IFERROR(VLOOKUP(C16,'Plan objetivo 10%'!$A:$C,3,FALSE),"")) | J16: =IF(OR(G16="",I16=""),"",G16-I16)
G17: =IF(F17="","",$B$4+SUM($F$9:F17)) | H17: =IF(F17="","",F17/(G17-F17)) | I17: =IF(C17="","",IFERROR(VLOOKUP(C17,'Plan objetivo 10%'!$A:$C,3,FALSE),"")) | J17: =IF(OR(G17="",I17=""),"",G17-I17)
G18: =IF(F18="","",$B$4+SUM($F$9:F18)) | H18: =IF(F18="","",F18/(G18-F18)) | I18: =IF(C18="","",IFERROR(VLOOKUP(C18,'Plan objetivo 10%'!$A:$C,3,FALSE),"")) | J18: =IF(OR(G18="",I18=""),"",G18-I18)
G19: =IF(F19="","",$B$4+SUM($F$9:F19)) | H19: =IF(F19="","",F19/(G19-F19)) | I19: =IF(C19="","",IFERROR(VLOOKUP(C19,'Plan objetivo 10%'!$A:$C,3,FALSE),"")) | J19: =IF(OR(G19="",I19=""),"",G19-I19)
G20: =IF(F20="","",$B$4+SUM($F$9:F20)) | H20: =IF(F20="","",F20/(G20-F20)) | I20: =IF(C20="","",IFERROR(VLOOKUP(C20,'Plan objetivo 10%'!$A:$C,3,FALSE),"")) | J20: =IF(OR(G20="",I20=""),"",G20-I20)
G21: =IF(F21="","",$B$4+SUM($F$9:F21)) | H21: =IF(F21="","",F21/(G21-F21)) | I21: =IF(C21="","",IFERROR(VLOOKUP(C21,'Plan objetivo 10%'!$A:$C,3,FALSE),"")) | J21: =IF(OR(G21="",I21=""),"",G21-I21)
G22: =IF(F22="","",$B$4+SUM($F$9:F22)) | H22: =IF(F22="","",F22/(G22-F22)) | I22: =IF(C22="","",IFERROR(VLOOKUP(C22,'Plan objetivo 10%'!$A:$C,3,FALSE),"")) | J22: =IF(OR(G22="",I22=""),"",G22-I22)
G23: =IF(F23="","",$B$4+SUM($F$9:F23)) | H23: =IF(F23="","",F23/(G23-F23)) | I23: =IF(C23="","",IFERROR(VLOOKUP(C23,'Plan objetivo 10%'!$A:$C,3,FALSE),"")) | J23: =IF(OR(G23="",I23=""),"",G23-I23)
G24: =IF(F24="","",$B$4+SUM($F$9:F24)) | H24: =IF(F24="","",F24/(G24-F24)) | I24: =IF(C24="","",IFERROR(VLOOKUP(C24,'Plan objetivo 10%'!$A:$C,3,FALSE),"")) | J24: =IF(OR(G24="",I24=""),"",G24-I24)
... G58: =IF(F58="","",$B$4+SUM($F$9:F58)) | H58: =IF(F58="","",F58/(G58-F58)) | I58: =IF(C58="","",IFERROR(VLOOKUP(C58,'Plan objetivo 10%'!$A:$C,3,FALSE),"")) | J58: =IF(OR(G58="",I58=""),"",G58-I58)
A61: COMO USARLO
A62: • Rellena las columnas AZULES cada dia: Fecha, Op #, Dia op., Activo, Rend. trade % y Ganancia ($).
A63: • Op # = numero de operacion (1,2,3...). Dia op. = numero de dia operado (si haces 2 trades el mismo dia, repite el mismo numero).
A64: • Rend. trade % = rendimiento del contrato (venta-compra)/compra. % s/ capital = cuanto ganaste ese dia respecto al capital previo (compara con el 10%).
A65: • Balance, % s/ capital, Balance objetivo y Dif. vs plan se calculan solos. Verde = vas por encima del plan; rojo = por debajo.
A66: • Los precios de compra/venta NO se guardan en la tabla, solo el %. Usa la calculadora de la derecha para obtenerlo.

Sheet Plan objetivo 10%
A1: PLAN OBJETIVO · Crecimiento 10% diario
A2: Proyeccion de referencia. Cambia la tasa o el capital y toda la curva se recalcula.
A3: Tasa diaria objetivo | B3: 0.1
A4: Capital inicial | B4: ='Registro real'!B4
A6: Dia | B6: Ganancia objetivo | C6: Balance objetivo
A7: 0 | B7: — | C7: =B4
A8: 1 | B8: =C7*$B$3 | C8: =C7*(1+$B$3)
A9: 2 | B9: =C8*$B$3 | C9: =C8*(1+$B$3)
A10: 3 | B10: =C9*$B$3 | C10: =C9*(1+$B$3)
A11: 4 | B11: =C10*$B$3 | C11: =C10*(1+$B$3)
A12: 5 | B12: =C11*$B$3 | C12: =C11*(1+$B$3)
A13: 6 | B13: =C12*$B$3 | C13: =C12*(1+$B$3)
A14: 7 | B14: =C13*$B$3 | C14: =C13*(1+$B$3)
A15: 8 | B15: =C14*$B$3 | C15: =C14*(1+$B$3)
A16: 9 | B16: =C15*$B$3 | C16: =C15*(1+$B$3)
A17: 10 | B17: =C16*$B$3 | C17: =C16*(1+$B$3)
A18: 11 | B18: =C17*$B$3 | C18: =C17*(1+$B$3)
A19: 12 | B19: =C18*$B$3 | C19: =C18*(1+$B$3)
... A37: 30 | B37: =C36*$B$3 | C37: =C36*(1+$B$3)
